[
  {
    "py/object": "model.group.Group",
    "name": "nameAm|,a",
    "header": "header 3+&k8~@Bks\\N",
    "footer": "footerEP ocv<S",
    "id": null
  },
  {
    "py/object": "model.group.Group",
    "name": "namea_ #j",
    "header": "header4zMv=K_P",
    "footer": "footer \\I",
    "id": null
  },
  {
    "py/object": "model.group.Group",
    "name": "name-7 !n",
    "header": "headeru7v6Cz\"W>",
    "footer": "footerb~  QI1",
    "id": null
  },
  {
    "py/object": "model.group.Group",
    "name": "nameac k",
    "header": "header}Hw5APS3\\dz8\"'x`D.u",
    "footer": "footer W8*[7X&x|C[T|\"om#4",
    "id": null
  },
  {
    "py/object": "model.group.Group",
    "name": "namer+!}R3i`A",
    "header": "header",
    "footer": "footer9E,/s:?W",
    "id": null
  }
]